quantmllib/__init__.py
quantmllib/backtest_statistics/__init__.py
quantmllib/backtest_statistics/backtests.py
quantmllib/backtest_statistics/statistics.py
quantmllib/bet_sizing/README.md
quantmllib/bet_sizing/__init__.py
quantmllib/bet_sizing/bet_sizing.py
quantmllib/bet_sizing/ch10_snippets.py
quantmllib/bet_sizing/ef3m.py
quantmllib/clustering/__init__.py
quantmllib/clustering/feature_clusters.py
quantmllib/clustering/hierarchical_clustering.py
quantmllib/clustering/onc.py
quantmllib/codependence/__init__.py
quantmllib/codependence/codependence_matrix.py
quantmllib/codependence/correlation.py
quantmllib/codependence/gnpr_distance.py
quantmllib/codependence/information.py
quantmllib/codependence/optimal_transport.py
quantmllib/cointegration_approach/__init__.py
quantmllib/cointegration_approach/base.py
quantmllib/cointegration_approach/coint_sim.py
quantmllib/cointegration_approach/engle_granger.py
quantmllib/cointegration_approach/johansen.py
quantmllib/cointegration_approach/minimum_profit.py
quantmllib/cointegration_approach/multi_coint.py
quantmllib/cointegration_approach/sparse_mr_portfolio.py
quantmllib/cointegration_approach/utils.py
quantmllib/cross_validation/__init__.py
quantmllib/cross_validation/combinatorial.py
quantmllib/cross_validation/cross_validation.py
quantmllib/data_generation/__init__.py
quantmllib/data_generation/bootstrap.py
quantmllib/data_generation/correlated_random_walks.py
quantmllib/data_generation/corrgan.py
quantmllib/data_generation/data_verification.py
quantmllib/data_generation/hcbm.py
quantmllib/data_generation/vines.py
quantmllib/data_structures/__init__.py
quantmllib/data_structures/base_bars.py
quantmllib/data_structures/imbalance_data_structures.py
quantmllib/data_structures/run_data_structures.py
quantmllib/data_structures/standard_data_structures.py
quantmllib/data_structures/time_data_structures.py
quantmllib/datasets/__init__.py
quantmllib/datasets/data/dollar_bar_sample.csv
quantmllib/datasets/data/stock_prices.csv
quantmllib-0.0.1.dev0.dist-info/WHEEL
quantmllib-0.0.1.dev0.dist-info/METADATA
quantmllib-0.0.1.dev0.dist-info/RECORD
